predlp/__init__.py
predlp/solver.py
predlp-0.1.1.dist-info/LICENSE
predlp-0.1.1.dist-info/METADATA
predlp-0.1.1.dist-info/WHEEL
predlp-0.1.1.dist-info/RECORD
