Metadata-Version: 2.1
Name: predlp
Version: 0.1.1
Summary: Prediction probabilities with a linear programming constraint during label assignment.
Author: Justin Evans
Author-email: 11je20@queensu.ca
Requires-Python: >=3.10,<4.0
Classifier: Programming Language :: Python :: 3
Classifier: Programming Language :: Python :: 3.10
Classifier: Programming Language :: Python :: 3.11
Classifier: Programming Language :: Python :: 3.12
Classifier: Programming Language :: Python :: 3.13
Requires-Dist: pulp (>=2.9.0,<3.0.0)
